<?xml version="1.0" encoding="UTF-8"?>
<!DOCTYPE mapper
      PUBLIC "-//mybatis.org//DTD Mapper 3.0//EN"
   "http://mybatis.org/dtd/mybatis-3-mapper.dtd">
<mapper namespace="Buy.P001.D004">
	<resultMap id="B_P001_D004Result01" type="B_P001_D004VO">
		<!-- order_num은 2 테이블 공통 사용-->
		<result property="order_num" column="order_num" />
		<!-- order 1번으로 insert -->
		<result property="seller_memberid" column="seller_memberid" />
		<result property="buyer_memberid" column="buyer_memberid" />
		<result property="order_date" column="order_date" />
		<result property="total_price" column="total_price" />
		<result property="order_fix_yn" column="order_fix_yn" />
		<result property="order_state" column="order_state" />
		<result property="order_want" column="order_want" />
		<result property="pay_method" column="pay_method" />
		<result property="pay_price" column="pay_price" />
		<result property="pay_group" column="pay_group" />
		<result property="pay_date" column="pay_date" />
		<!-- orderitems  2번 insert -->
		<result property="prod_number" column="prod_number" />
		<result property="quantity" column="quantity" />
		<result property="item_price" column="item_price" />
		<result property="get_method" column="get_method" />
	</resultMap>
	<insert id="insertOrder">
		<![CDATA[
         insert into cart()
            values()
	  ]]>
	</insert>
	<insert id="insertOrderitesm">
		<![CDATA[
         insert into cart()
            values 
	  ]]>
	</insert>
</mapper>